[
  {
    "id": "d90f203922a4b3dd",
    "deck": "03_Languages::English::Phonetics_and_Connected_Speech::01_Cluster_Elision",
    "template": "T9_ListeningChunk",
    "metadata": {
      "difficulty": "intermediate",
      "pillar": "03_Languages",
      "tags": [
        "english",
        "phonetics",
        "connected_speech",
        "cluster_elision",
        "tier_1",
        "cluster_elision"
      ]
    },
    "content": {
      "scenario": "Listening Chunk 🎧: Connected Speech (EN)",
      "text": "<a href=\"https://youglish.com/pronounce/last%20night/english/us\" target=\"_blank\">🎧 YouGlish: Hear in context</a> &nbsp;|&nbsp; <a href=\"https://forvo.com/word/last/#en\" target=\"_blank\">🔊 Forvo: Isolated word</a><br><br><b>Fill the gap:</b><br>I went to sleep late {{c1::last night}}.",
      "explanation": "<b>Full transcript:</b> last night<br><br><b>Connected form:</b> <i>las night</i><br><br><b>Phonetic rules applied:</b><ul><li><code>Cluster Elision</code></li></ul>",
      "spanish": "anoche",
      "usage": "Native: <code>las night</code><br>Formal: <code>last night</code><br><a href=\"https://youglish.com/pronounce/last%20night/english/us\" target=\"_blank\">🎧 YouGlish: Hear in context</a> &nbsp;|&nbsp; <a href=\"https://forvo.com/word/last/#en\" target=\"_blank\">🔊 Forvo: Isolated word</a>",
      "id": "d90f203922a4b3dd",
      "full_transcript": "last night",
      "connected_form": "las night",
      "gap_text": "I went to sleep late {{c1::last night}}.",
      "rules_applied": [
        "Cluster Elision"
      ],
      "language": "en",
      "audio_links": {
        "youglish_phrase": "https://youglish.com/pronounce/last%20night/english/us",
        "forvo_word": "https://forvo.com/word/last/#en"
      }
    },
    "mnemonics": {
      "palace_name": "",
      "locus_stop": "",
      "mnemonic_scene": "",
      "peg_word": "",
      "phonetic_code": ""
    },
    "interactivity": {
      "analogy": "",
      "interactive_mermaid": "",
      "match_game_data": null
    }
  },
  {
    "id": "a50fdaffe7b79a86",
    "deck": "03_Languages::English::Phonetics_and_Connected_Speech::01_Cluster_Elision",
    "template": "T9_ListeningChunk",
    "metadata": {
      "difficulty": "intermediate",
      "pillar": "03_Languages",
      "tags": [
        "english",
        "phonetics",
        "connected_speech",
        "cluster_elision",
        "tier_1",
        "cluster_elision"
      ]
    },
    "content": {
      "scenario": "Listening Chunk 🎧: Connected Speech (EN)",
      "text": "<a href=\"https://youglish.com/pronounce/next%20door/english/us\" target=\"_blank\">🎧 YouGlish: Hear in context</a> &nbsp;|&nbsp; <a href=\"https://forvo.com/word/next/#en\" target=\"_blank\">🔊 Forvo: Isolated word</a><br><br><b>Fill the gap:</b><br>He lives {{c1::next door}} to me.",
      "explanation": "<b>Full transcript:</b> next door<br><br><b>Connected form:</b> <i>nex door</i><br><br><b>Phonetic rules applied:</b><ul><li><code>Cluster Elision</code></li></ul>",
      "spanish": "al lado",
      "usage": "Native: <code>nex door</code><br>Formal: <code>next door</code><br><a href=\"https://youglish.com/pronounce/next%20door/english/us\" target=\"_blank\">🎧 YouGlish: Hear in context</a> &nbsp;|&nbsp; <a href=\"https://forvo.com/word/next/#en\" target=\"_blank\">🔊 Forvo: Isolated word</a>",
      "id": "a50fdaffe7b79a86",
      "full_transcript": "next door",
      "connected_form": "nex door",
      "gap_text": "He lives {{c1::next door}} to me.",
      "rules_applied": [
        "Cluster Elision"
      ],
      "language": "en",
      "audio_links": {
        "youglish_phrase": "https://youglish.com/pronounce/next%20door/english/us",
        "forvo_word": "https://forvo.com/word/next/#en"
      }
    },
    "mnemonics": {
      "palace_name": "",
      "locus_stop": "",
      "mnemonic_scene": "",
      "peg_word": "",
      "phonetic_code": ""
    },
    "interactivity": {
      "analogy": "",
      "interactive_mermaid": "",
      "match_game_data": null
    }
  },
  {
    "id": "076cb8f6a7b6a36a",
    "deck": "03_Languages::English::Phonetics_and_Connected_Speech::01_Cluster_Elision",
    "template": "T9_ListeningChunk",
    "metadata": {
      "difficulty": "intermediate",
      "pillar": "03_Languages",
      "tags": [
        "english",
        "phonetics",
        "connected_speech",
        "cluster_elision",
        "tier_1",
        "cluster_elision"
      ]
    },
    "content": {
      "scenario": "Listening Chunk 🎧: Connected Speech (EN)",
      "text": "<a href=\"https://youglish.com/pronounce/must%20be/english/us\" target=\"_blank\">🎧 YouGlish: Hear in context</a> &nbsp;|&nbsp; <a href=\"https://forvo.com/word/must/#en\" target=\"_blank\">🔊 Forvo: Isolated word</a><br><br><b>Fill the gap:</b><br>That {{c1::must be}} the answer.",
      "explanation": "<b>Full transcript:</b> must be<br><br><b>Connected form:</b> <i>mus be</i><br><br><b>Phonetic rules applied:</b><ul><li><code>Cluster Elision</code></li></ul>",
      "spanish": "debe ser",
      "usage": "Native: <code>mus be</code><br>Formal: <code>must be</code><br><a href=\"https://youglish.com/pronounce/must%20be/english/us\" target=\"_blank\">🎧 YouGlish: Hear in context</a> &nbsp;|&nbsp; <a href=\"https://forvo.com/word/must/#en\" target=\"_blank\">🔊 Forvo: Isolated word</a>",
      "id": "076cb8f6a7b6a36a",
      "full_transcript": "must be",
      "connected_form": "mus be",
      "gap_text": "That {{c1::must be}} the answer.",
      "rules_applied": [
        "Cluster Elision"
      ],
      "language": "en",
      "audio_links": {
        "youglish_phrase": "https://youglish.com/pronounce/must%20be/english/us",
        "forvo_word": "https://forvo.com/word/must/#en"
      }
    },
    "mnemonics": {
      "palace_name": "",
      "locus_stop": "",
      "mnemonic_scene": "",
      "peg_word": "",
      "phonetic_code": ""
    },
    "interactivity": {
      "analogy": "",
      "interactive_mermaid": "",
      "match_game_data": null
    }
  },
  {
    "id": "3fac53c94bed1347",
    "deck": "03_Languages::English::Phonetics_and_Connected_Speech::01_Cluster_Elision",
    "template": "T9_ListeningChunk",
    "metadata": {
      "difficulty": "intermediate",
      "pillar": "03_Languages",
      "tags": [
        "english",
        "phonetics",
        "connected_speech",
        "cluster_elision",
        "tier_1",
        "cluster_elision"
      ]
    },
    "content": {
      "scenario": "Listening Chunk 🎧: Connected Speech (EN)",
      "text": "<a href=\"https://youglish.com/pronounce/just%20one/english/us\" target=\"_blank\">🎧 YouGlish: Hear in context</a> &nbsp;|&nbsp; <a href=\"https://forvo.com/word/just/#en\" target=\"_blank\">🔊 Forvo: Isolated word</a><br><br><b>Fill the gap:</b><br>I only want {{c1::just one}} piece.",
      "explanation": "<b>Full transcript:</b> just one<br><br><b>Connected form:</b> <i>jus one</i><br><br><b>Phonetic rules applied:</b><ul><li><code>Cluster Elision</code></li></ul>",
      "spanish": "solo uno",
      "usage": "Native: <code>jus one</code><br>Formal: <code>just one</code><br><a href=\"https://youglish.com/pronounce/just%20one/english/us\" target=\"_blank\">🎧 YouGlish: Hear in context</a> &nbsp;|&nbsp; <a href=\"https://forvo.com/word/just/#en\" target=\"_blank\">🔊 Forvo: Isolated word</a>",
      "id": "3fac53c94bed1347",
      "full_transcript": "just one",
      "connected_form": "jus one",
      "gap_text": "I only want {{c1::just one}} piece.",
      "rules_applied": [
        "Cluster Elision"
      ],
      "language": "en",
      "audio_links": {
        "youglish_phrase": "https://youglish.com/pronounce/just%20one/english/us",
        "forvo_word": "https://forvo.com/word/just/#en"
      }
    },
    "mnemonics": {
      "palace_name": "",
      "locus_stop": "",
      "mnemonic_scene": "",
      "peg_word": "",
      "phonetic_code": ""
    },
    "interactivity": {
      "analogy": "",
      "interactive_mermaid": "",
      "match_game_data": null
    }
  },
  {
    "id": "efed593373183a60",
    "deck": "03_Languages::English::Phonetics_and_Connected_Speech::01_Cluster_Elision",
    "template": "T9_ListeningChunk",
    "metadata": {
      "difficulty": "intermediate",
      "pillar": "03_Languages",
      "tags": [
        "english",
        "phonetics",
        "connected_speech",
        "cluster_elision",
        "tier_1",
        "cluster_elision"
      ]
    },
    "content": {
      "scenario": "Listening Chunk 🎧: Connected Speech (EN)",
      "text": "<a href=\"https://youglish.com/pronounce/best%20friend/english/us\" target=\"_blank\">🎧 YouGlish: Hear in context</a> &nbsp;|&nbsp; <a href=\"https://forvo.com/word/best/#en\" target=\"_blank\">🔊 Forvo: Isolated word</a><br><br><b>Fill the gap:</b><br>She is my {{c1::best friend}}.",
      "explanation": "<b>Full transcript:</b> best friend<br><br><b>Connected form:</b> <i>bes friend</i><br><br><b>Phonetic rules applied:</b><ul><li><code>Cluster Elision</code></li></ul>",
      "spanish": "mejor amigo",
      "usage": "Native: <code>bes friend</code><br>Formal: <code>best friend</code><br><a href=\"https://youglish.com/pronounce/best%20friend/english/us\" target=\"_blank\">🎧 YouGlish: Hear in context</a> &nbsp;|&nbsp; <a href=\"https://forvo.com/word/best/#en\" target=\"_blank\">🔊 Forvo: Isolated word</a>",
      "id": "efed593373183a60",
      "full_transcript": "best friend",
      "connected_form": "bes friend",
      "gap_text": "She is my {{c1::best friend}}.",
      "rules_applied": [
        "Cluster Elision"
      ],
      "language": "en",
      "audio_links": {
        "youglish_phrase": "https://youglish.com/pronounce/best%20friend/english/us",
        "forvo_word": "https://forvo.com/word/best/#en"
      }
    },
    "mnemonics": {
      "palace_name": "",
      "locus_stop": "",
      "mnemonic_scene": "",
      "peg_word": "",
      "phonetic_code": ""
    },
    "interactivity": {
      "analogy": "",
      "interactive_mermaid": "",
      "match_game_data": null
    }
  },
  {
    "id": "1572600beceaec93",
    "deck": "03_Languages::English::Phonetics_and_Connected_Speech::01_Cluster_Elision",
    "template": "T9_ListeningChunk",
    "metadata": {
      "difficulty": "intermediate",
      "pillar": "03_Languages",
      "tags": [
        "english",
        "phonetics",
        "connected_speech",
        "cluster_elision",
        "tier_1",
        "cluster_elision"
      ]
    },
    "content": {
      "scenario": "Listening Chunk 🎧: Connected Speech (EN)",
      "text": "<a href=\"https://youglish.com/pronounce/cold%20drink/english/us\" target=\"_blank\">🎧 YouGlish: Hear in context</a> &nbsp;|&nbsp; <a href=\"https://forvo.com/word/cold/#en\" target=\"_blank\">🔊 Forvo: Isolated word</a><br><br><b>Fill the gap:</b><br>Would you like a {{c1::cold drink}}?",
      "explanation": "<b>Full transcript:</b> cold drink<br><br><b>Connected form:</b> <i>col drink</i><br><br><b>Phonetic rules applied:</b><ul><li><code>Cluster Elision</code></li></ul>",
      "spanish": "bebida fría",
      "usage": "Native: <code>col drink</code><br>Formal: <code>cold drink</code><br><a href=\"https://youglish.com/pronounce/cold%20drink/english/us\" target=\"_blank\">🎧 YouGlish: Hear in context</a> &nbsp;|&nbsp; <a href=\"https://forvo.com/word/cold/#en\" target=\"_blank\">🔊 Forvo: Isolated word</a>",
      "id": "1572600beceaec93",
      "full_transcript": "cold drink",
      "connected_form": "col drink",
      "gap_text": "Would you like a {{c1::cold drink}}?",
      "rules_applied": [
        "Cluster Elision"
      ],
      "language": "en",
      "audio_links": {
        "youglish_phrase": "https://youglish.com/pronounce/cold%20drink/english/us",
        "forvo_word": "https://forvo.com/word/cold/#en"
      }
    },
    "mnemonics": {
      "palace_name": "",
      "locus_stop": "",
      "mnemonic_scene": "",
      "peg_word": "",
      "phonetic_code": ""
    },
    "interactivity": {
      "analogy": "",
      "interactive_mermaid": "",
      "match_game_data": null
    }
  },
  {
    "id": "a067422a441cc291",
    "deck": "03_Languages::English::Phonetics_and_Connected_Speech::01_Cluster_Elision",
    "template": "T9_ListeningChunk",
    "metadata": {
      "difficulty": "intermediate",
      "pillar": "03_Languages",
      "tags": [
        "english",
        "phonetics",
        "connected_speech",
        "cluster_elision",
        "tier_1",
        "cluster_elision"
      ]
    },
    "content": {
      "scenario": "Listening Chunk 🎧: Connected Speech (EN)",
      "text": "<a href=\"https://youglish.com/pronounce/old%20man/english/us\" target=\"_blank\">🎧 YouGlish: Hear in context</a> &nbsp;|&nbsp; <a href=\"https://forvo.com/word/old/#en\" target=\"_blank\">🔊 Forvo: Isolated word</a><br><br><b>Fill the gap:</b><br>The {{c1::old man}} walked slowly.",
      "explanation": "<b>Full transcript:</b> old man<br><br><b>Connected form:</b> <i>ol man</i><br><br><b>Phonetic rules applied:</b><ul><li><code>Cluster Elision</code></li></ul>",
      "spanish": "hombre viejo",
      "usage": "Native: <code>ol man</code><br>Formal: <code>old man</code><br><a href=\"https://youglish.com/pronounce/old%20man/english/us\" target=\"_blank\">🎧 YouGlish: Hear in context</a> &nbsp;|&nbsp; <a href=\"https://forvo.com/word/old/#en\" target=\"_blank\">🔊 Forvo: Isolated word</a>",
      "id": "a067422a441cc291",
      "full_transcript": "old man",
      "connected_form": "ol man",
      "gap_text": "The {{c1::old man}} walked slowly.",
      "rules_applied": [
        "Cluster Elision"
      ],
      "language": "en",
      "audio_links": {
        "youglish_phrase": "https://youglish.com/pronounce/old%20man/english/us",
        "forvo_word": "https://forvo.com/word/old/#en"
      }
    },
    "mnemonics": {
      "palace_name": "",
      "locus_stop": "",
      "mnemonic_scene": "",
      "peg_word": "",
      "phonetic_code": ""
    },
    "interactivity": {
      "analogy": "",
      "interactive_mermaid": "",
      "match_game_data": null
    }
  },
  {
    "id": "2ff27ee78a637691",
    "deck": "03_Languages::English::Phonetics_and_Connected_Speech::01_Cluster_Elision",
    "template": "T9_ListeningChunk",
    "metadata": {
      "difficulty": "intermediate",
      "pillar": "03_Languages",
      "tags": [
        "english",
        "phonetics",
        "connected_speech",
        "cluster_elision",
        "tier_1",
        "cluster_elision"
      ]
    },
    "content": {
      "scenario": "Listening Chunk 🎧: Connected Speech (EN)",
      "text": "<a href=\"https://youglish.com/pronounce/first%20time/english/us\" target=\"_blank\">🎧 YouGlish: Hear in context</a> &nbsp;|&nbsp; <a href=\"https://forvo.com/word/first/#en\" target=\"_blank\">🔊 Forvo: Isolated word</a><br><br><b>Fill the gap:</b><br>This is the {{c1::first time}} I've been here.",
      "explanation": "<b>Full transcript:</b> first time<br><br><b>Connected form:</b> <i>firs time</i><br><br><b>Phonetic rules applied:</b><ul><li><code>Cluster Elision</code></li></ul>",
      "spanish": "primera vez",
      "usage": "Native: <code>firs time</code><br>Formal: <code>first time</code><br><a href=\"https://youglish.com/pronounce/first%20time/english/us\" target=\"_blank\">🎧 YouGlish: Hear in context</a> &nbsp;|&nbsp; <a href=\"https://forvo.com/word/first/#en\" target=\"_blank\">🔊 Forvo: Isolated word</a>",
      "id": "2ff27ee78a637691",
      "full_transcript": "first time",
      "connected_form": "firs time",
      "gap_text": "This is the {{c1::first time}} I've been here.",
      "rules_applied": [
        "Cluster Elision"
      ],
      "language": "en",
      "audio_links": {
        "youglish_phrase": "https://youglish.com/pronounce/first%20time/english/us",
        "forvo_word": "https://forvo.com/word/first/#en"
      }
    },
    "mnemonics": {
      "palace_name": "",
      "locus_stop": "",
      "mnemonic_scene": "",
      "peg_word": "",
      "phonetic_code": ""
    },
    "interactivity": {
      "analogy": "",
      "interactive_mermaid": "",
      "match_game_data": null
    }
  },
  {
    "id": "ef65370e6d309b4e",
    "deck": "03_Languages::English::Phonetics_and_Connected_Speech::01_Cluster_Elision",
    "template": "T9_ListeningChunk",
    "metadata": {
      "difficulty": "intermediate",
      "pillar": "03_Languages",
      "tags": [
        "english",
        "phonetics",
        "connected_speech",
        "cluster_elision",
        "tier_1",
        "cluster_elision"
      ]
    },
    "content": {
      "scenario": "Listening Chunk 🎧: Connected Speech (EN)",
      "text": "<a href=\"https://youglish.com/pronounce/last%20time/english/us\" target=\"_blank\">🎧 YouGlish: Hear in context</a> &nbsp;|&nbsp; <a href=\"https://forvo.com/word/last/#en\" target=\"_blank\">🔊 Forvo: Isolated word</a><br><br><b>Fill the gap:</b><br>That was the {{c1::last time}} I saw him.",
      "explanation": "<b>Full transcript:</b> last time<br><br><b>Connected form:</b> <i>las time</i><br><br><b>Phonetic rules applied:</b><ul><li><code>Cluster Elision</code></li></ul>",
      "spanish": "última vez",
      "usage": "Native: <code>las time</code><br>Formal: <code>last time</code><br><a href=\"https://youglish.com/pronounce/last%20time/english/us\" target=\"_blank\">🎧 YouGlish: Hear in context</a> &nbsp;|&nbsp; <a href=\"https://forvo.com/word/last/#en\" target=\"_blank\">🔊 Forvo: Isolated word</a>",
      "id": "ef65370e6d309b4e",
      "full_transcript": "last time",
      "connected_form": "las time",
      "gap_text": "That was the {{c1::last time}} I saw him.",
      "rules_applied": [
        "Cluster Elision"
      ],
      "language": "en",
      "audio_links": {
        "youglish_phrase": "https://youglish.com/pronounce/last%20time/english/us",
        "forvo_word": "https://forvo.com/word/last/#en"
      }
    },
    "mnemonics": {
      "palace_name": "",
      "locus_stop": "",
      "mnemonic_scene": "",
      "peg_word": "",
      "phonetic_code": ""
    },
    "interactivity": {
      "analogy": "",
      "interactive_mermaid": "",
      "match_game_data": null
    }
  },
  {
    "id": "52794261d72ecc44",
    "deck": "03_Languages::English::Phonetics_and_Connected_Speech::01_Cluster_Elision",
    "template": "T9_ListeningChunk",
    "metadata": {
      "difficulty": "intermediate",
      "pillar": "03_Languages",
      "tags": [
        "english",
        "phonetics",
        "connected_speech",
        "cluster_elision",
        "tier_1",
        "cluster_elision"
      ]
    },
    "content": {
      "scenario": "Listening Chunk 🎧: Connected Speech (EN)",
      "text": "<a href=\"https://youglish.com/pronounce/next%20time/english/us\" target=\"_blank\">🎧 YouGlish: Hear in context</a> &nbsp;|&nbsp; <a href=\"https://forvo.com/word/next/#en\" target=\"_blank\">🔊 Forvo: Isolated word</a><br><br><b>Fill the gap:</b><br>We'll do better {{c1::next time}}.",
      "explanation": "<b>Full transcript:</b> next time<br><br><b>Connected form:</b> <i>nex time</i><br><br><b>Phonetic rules applied:</b><ul><li><code>Cluster Elision</code></li></ul>",
      "spanish": "próxima vez",
      "usage": "Native: <code>nex time</code><br>Formal: <code>next time</code><br><a href=\"https://youglish.com/pronounce/next%20time/english/us\" target=\"_blank\">🎧 YouGlish: Hear in context</a> &nbsp;|&nbsp; <a href=\"https://forvo.com/word/next/#en\" target=\"_blank\">🔊 Forvo: Isolated word</a>",
      "id": "52794261d72ecc44",
      "full_transcript": "next time",
      "connected_form": "nex time",
      "gap_text": "We'll do better {{c1::next time}}.",
      "rules_applied": [
        "Cluster Elision"
      ],
      "language": "en",
      "audio_links": {
        "youglish_phrase": "https://youglish.com/pronounce/next%20time/english/us",
        "forvo_word": "https://forvo.com/word/next/#en"
      }
    },
    "mnemonics": {
      "palace_name": "",
      "locus_stop": "",
      "mnemonic_scene": "",
      "peg_word": "",
      "phonetic_code": ""
    },
    "interactivity": {
      "analogy": "",
      "interactive_mermaid": "",
      "match_game_data": null
    }
  },
  {
    "id": "37634df5749b60cb",
    "deck": "03_Languages::English::Phonetics_and_Connected_Speech::01_Cluster_Elision",
    "template": "T9_ListeningChunk",
    "metadata": {
      "difficulty": "intermediate",
      "pillar": "03_Languages",
      "tags": [
        "english",
        "phonetics",
        "connected_speech",
        "cluster_elision",
        "tier_2",
        "cluster_elision"
      ]
    },
    "content": {
      "scenario": "Listening Chunk 🎧: Connected Speech (EN)",
      "text": "<a href=\"https://youglish.com/pronounce/left%20side/english/us\" target=\"_blank\">🎧 YouGlish: Hear in context</a> &nbsp;|&nbsp; <a href=\"https://forvo.com/word/left/#en\" target=\"_blank\">🔊 Forvo: Isolated word</a><br><br><b>Fill the gap:</b><br>Turn on the {{c1::left side}} of the street.",
      "explanation": "<b>Full transcript:</b> left side<br><br><b>Connected form:</b> <i>lef side</i><br><br><b>Phonetic rules applied:</b><ul><li><code>Cluster Elision</code></li></ul>",
      "spanish": "lado izquierdo",
      "usage": "Native: <code>lef side</code><br>Formal: <code>left side</code><br><a href=\"https://youglish.com/pronounce/left%20side/english/us\" target=\"_blank\">🎧 YouGlish: Hear in context</a> &nbsp;|&nbsp; <a href=\"https://forvo.com/word/left/#en\" target=\"_blank\">🔊 Forvo: Isolated word</a>",
      "id": "37634df5749b60cb",
      "full_transcript": "left side",
      "connected_form": "lef side",
      "gap_text": "Turn on the {{c1::left side}} of the street.",
      "rules_applied": [
        "Cluster Elision"
      ],
      "language": "en",
      "audio_links": {
        "youglish_phrase": "https://youglish.com/pronounce/left%20side/english/us",
        "forvo_word": "https://forvo.com/word/left/#en"
      }
    },
    "mnemonics": {
      "palace_name": "",
      "locus_stop": "",
      "mnemonic_scene": "",
      "peg_word": "",
      "phonetic_code": ""
    },
    "interactivity": {
      "analogy": "",
      "interactive_mermaid": "",
      "match_game_data": null
    }
  },
  {
    "id": "8a0e12ac2b4de436",
    "deck": "03_Languages::English::Phonetics_and_Connected_Speech::01_Cluster_Elision",
    "template": "T9_ListeningChunk",
    "metadata": {
      "difficulty": "intermediate",
      "pillar": "03_Languages",
      "tags": [
        "english",
        "phonetics",
        "connected_speech",
        "cluster_elision",
        "tier_2",
        "cluster_elision"
      ]
    },
    "content": {
      "scenario": "Listening Chunk 🎧: Connected Speech (EN)",
      "text": "<a href=\"https://youglish.com/pronounce/right%20now/english/us\" target=\"_blank\">🎧 YouGlish: Hear in context</a> &nbsp;|&nbsp; <a href=\"https://forvo.com/word/right/#en\" target=\"_blank\">🔊 Forvo: Isolated word</a><br><br><b>Fill the gap:</b><br>I need you to do it {{c1::right now}}.",
      "explanation": "<b>Full transcript:</b> right now<br><br><b>Connected form:</b> <i>righ now</i><br><br><b>Phonetic rules applied:</b><ul><li><code>Cluster Elision</code></li></ul>",
      "spanish": "ahora mismo",
      "usage": "Native: <code>righ now</code><br>Formal: <code>right now</code><br><a href=\"https://youglish.com/pronounce/right%20now/english/us\" target=\"_blank\">🎧 YouGlish: Hear in context</a> &nbsp;|&nbsp; <a href=\"https://forvo.com/word/right/#en\" target=\"_blank\">🔊 Forvo: Isolated word</a>",
      "id": "8a0e12ac2b4de436",
      "full_transcript": "right now",
      "connected_form": "righ now",
      "gap_text": "I need you to do it {{c1::right now}}.",
      "rules_applied": [
        "Cluster Elision"
      ],
      "language": "en",
      "audio_links": {
        "youglish_phrase": "https://youglish.com/pronounce/right%20now/english/us",
        "forvo_word": "https://forvo.com/word/right/#en"
      }
    },
    "mnemonics": {
      "palace_name": "",
      "locus_stop": "",
      "mnemonic_scene": "",
      "peg_word": "",
      "phonetic_code": ""
    },
    "interactivity": {
      "analogy": "",
      "interactive_mermaid": "",
      "match_game_data": null
    }
  },
  {
    "id": "26376f9de4bb35cd",
    "deck": "03_Languages::English::Phonetics_and_Connected_Speech::01_Cluster_Elision",
    "template": "T9_ListeningChunk",
    "metadata": {
      "difficulty": "intermediate",
      "pillar": "03_Languages",
      "tags": [
        "english",
        "phonetics",
        "connected_speech",
        "cluster_elision",
        "tier_2",
        "cluster_elision"
      ]
    },
    "content": {
      "scenario": "Listening Chunk 🎧: Connected Speech (EN)",
      "text": "<a href=\"https://youglish.com/pronounce/just%20now/english/us\" target=\"_blank\">🎧 YouGlish: Hear in context</a> &nbsp;|&nbsp; <a href=\"https://forvo.com/word/just/#en\" target=\"_blank\">🔊 Forvo: Isolated word</a><br><br><b>Fill the gap:</b><br>He left the office {{c1::just now}}.",
      "explanation": "<b>Full transcript:</b> just now<br><br><b>Connected form:</b> <i>jus now</i><br><br><b>Phonetic rules applied:</b><ul><li><code>Cluster Elision</code></li></ul>",
      "spanish": "hace un momento",
      "usage": "Native: <code>jus now</code><br>Formal: <code>just now</code><br><a href=\"https://youglish.com/pronounce/just%20now/english/us\" target=\"_blank\">🎧 YouGlish: Hear in context</a> &nbsp;|&nbsp; <a href=\"https://forvo.com/word/just/#en\" target=\"_blank\">🔊 Forvo: Isolated word</a>",
      "id": "26376f9de4bb35cd",
      "full_transcript": "just now",
      "connected_form": "jus now",
      "gap_text": "He left the office {{c1::just now}}.",
      "rules_applied": [
        "Cluster Elision"
      ],
      "language": "en",
      "audio_links": {
        "youglish_phrase": "https://youglish.com/pronounce/just%20now/english/us",
        "forvo_word": "https://forvo.com/word/just/#en"
      }
    },
    "mnemonics": {
      "palace_name": "",
      "locus_stop": "",
      "mnemonic_scene": "",
      "peg_word": "",
      "phonetic_code": ""
    },
    "interactivity": {
      "analogy": "",
      "interactive_mermaid": "",
      "match_game_data": null
    }
  },
  {
    "id": "83943b876ab19a93",
    "deck": "03_Languages::English::Phonetics_and_Connected_Speech::01_Cluster_Elision",
    "template": "T9_ListeningChunk",
    "metadata": {
      "difficulty": "intermediate",
      "pillar": "03_Languages",
      "tags": [
        "english",
        "phonetics",
        "connected_speech",
        "cluster_elision",
        "tier_2",
        "cluster_elision"
      ]
    },
    "content": {
      "scenario": "Listening Chunk 🎧: Connected Speech (EN)",
      "text": "<a href=\"https://youglish.com/pronounce/soft%20drink/english/us\" target=\"_blank\">🎧 YouGlish: Hear in context</a> &nbsp;|&nbsp; <a href=\"https://forvo.com/word/soft/#en\" target=\"_blank\">🔊 Forvo: Isolated word</a><br><br><b>Fill the gap:</b><br>Do you want a {{c1::soft drink}} or water?",
      "explanation": "<b>Full transcript:</b> soft drink<br><br><b>Connected form:</b> <i>sof drink</i><br><br><b>Phonetic rules applied:</b><ul><li><code>Cluster Elision</code></li></ul>",
      "spanish": "refresco",
      "usage": "Native: <code>sof drink</code><br>Formal: <code>soft drink</code><br><a href=\"https://youglish.com/pronounce/soft%20drink/english/us\" target=\"_blank\">🎧 YouGlish: Hear in context</a> &nbsp;|&nbsp; <a href=\"https://forvo.com/word/soft/#en\" target=\"_blank\">🔊 Forvo: Isolated word</a>",
      "id": "83943b876ab19a93",
      "full_transcript": "soft drink",
      "connected_form": "sof drink",
      "gap_text": "Do you want a {{c1::soft drink}} or water?",
      "rules_applied": [
        "Cluster Elision"
      ],
      "language": "en",
      "audio_links": {
        "youglish_phrase": "https://youglish.com/pronounce/soft%20drink/english/us",
        "forvo_word": "https://forvo.com/word/soft/#en"
      }
    },
    "mnemonics": {
      "palace_name": "",
      "locus_stop": "",
      "mnemonic_scene": "",
      "peg_word": "",
      "phonetic_code": ""
    },
    "interactivity": {
      "analogy": "",
      "interactive_mermaid": "",
      "match_game_data": null
    }
  },
  {
    "id": "817b821f036599b9",
    "deck": "03_Languages::English::Phonetics_and_Connected_Speech::01_Cluster_Elision",
    "template": "T9_ListeningChunk",
    "metadata": {
      "difficulty": "intermediate",
      "pillar": "03_Languages",
      "tags": [
        "english",
        "phonetics",
        "connected_speech",
        "cluster_elision",
        "tier_2",
        "cluster_elision"
      ]
    },
    "content": {
      "scenario": "Listening Chunk 🎧: Connected Speech (EN)",
      "text": "<a href=\"https://youglish.com/pronounce/hand%20bag/english/us\" target=\"_blank\">🎧 YouGlish: Hear in context</a> &nbsp;|&nbsp; <a href=\"https://forvo.com/word/hand/#en\" target=\"_blank\">🔊 Forvo: Isolated word</a><br><br><b>Fill the gap:</b><br>She carried a small {{c1::hand bag}}.",
      "explanation": "<b>Full transcript:</b> hand bag<br><br><b>Connected form:</b> <i>han bag</i><br><br><b>Phonetic rules applied:</b><ul><li><code>Cluster Elision</code></li></ul>",
      "spanish": "bolso de mano",
      "usage": "Native: <code>han bag</code><br>Formal: <code>hand bag</code><br><a href=\"https://youglish.com/pronounce/hand%20bag/english/us\" target=\"_blank\">🎧 YouGlish: Hear in context</a> &nbsp;|&nbsp; <a href=\"https://forvo.com/word/hand/#en\" target=\"_blank\">🔊 Forvo: Isolated word</a>",
      "id": "817b821f036599b9",
      "full_transcript": "hand bag",
      "connected_form": "han bag",
      "gap_text": "She carried a small {{c1::hand bag}}.",
      "rules_applied": [
        "Cluster Elision"
      ],
      "language": "en",
      "audio_links": {
        "youglish_phrase": "https://youglish.com/pronounce/hand%20bag/english/us",
        "forvo_word": "https://forvo.com/word/hand/#en"
      }
    },
    "mnemonics": {
      "palace_name": "",
      "locus_stop": "",
      "mnemonic_scene": "",
      "peg_word": "",
      "phonetic_code": ""
    },
    "interactivity": {
      "analogy": "",
      "interactive_mermaid": "",
      "match_game_data": null
    }
  },
  {
    "id": "c69eb0564ce7fffe",
    "deck": "03_Languages::English::Phonetics_and_Connected_Speech::01_Cluster_Elision",
    "template": "T9_ListeningChunk",
    "metadata": {
      "difficulty": "intermediate",
      "pillar": "03_Languages",
      "tags": [
        "english",
        "phonetics",
        "connected_speech",
        "cluster_elision",
        "tier_2",
        "cluster_elision"
      ]
    },
    "content": {
      "scenario": "Listening Chunk 🎧: Connected Speech (EN)",
      "text": "<a href=\"https://youglish.com/pronounce/sand%20castle/english/us\" target=\"_blank\">🎧 YouGlish: Hear in context</a> &nbsp;|&nbsp; <a href=\"https://forvo.com/word/sand/#en\" target=\"_blank\">🔊 Forvo: Isolated word</a><br><br><b>Fill the gap:</b><br>They built a {{c1::sand castle}} on the beach.",
      "explanation": "<b>Full transcript:</b> sand castle<br><br><b>Connected form:</b> <i>san castle</i><br><br><b>Phonetic rules applied:</b><ul><li><code>Cluster Elision</code></li></ul>",
      "spanish": "castillo de arena",
      "usage": "Native: <code>san castle</code><br>Formal: <code>sand castle</code><br><a href=\"https://youglish.com/pronounce/sand%20castle/english/us\" target=\"_blank\">🎧 YouGlish: Hear in context</a> &nbsp;|&nbsp; <a href=\"https://forvo.com/word/sand/#en\" target=\"_blank\">🔊 Forvo: Isolated word</a>",
      "id": "c69eb0564ce7fffe",
      "full_transcript": "sand castle",
      "connected_form": "san castle",
      "gap_text": "They built a {{c1::sand castle}} on the beach.",
      "rules_applied": [
        "Cluster Elision"
      ],
      "language": "en",
      "audio_links": {
        "youglish_phrase": "https://youglish.com/pronounce/sand%20castle/english/us",
        "forvo_word": "https://forvo.com/word/sand/#en"
      }
    },
    "mnemonics": {
      "palace_name": "",
      "locus_stop": "",
      "mnemonic_scene": "",
      "peg_word": "",
      "phonetic_code": ""
    },
    "interactivity": {
      "analogy": "",
      "interactive_mermaid": "",
      "match_game_data": null
    }
  },
  {
    "id": "28f50dc1ec59db4f",
    "deck": "03_Languages::English::Phonetics_and_Connected_Speech::01_Cluster_Elision",
    "template": "T9_ListeningChunk",
    "metadata": {
      "difficulty": "intermediate",
      "pillar": "03_Languages",
      "tags": [
        "english",
        "phonetics",
        "connected_speech",
        "cluster_elision",
        "tier_2",
        "cluster_elision"
      ]
    },
    "content": {
      "scenario": "Listening Chunk 🎧: Connected Speech (EN)",
      "text": "<a href=\"https://youglish.com/pronounce/blind%20man/english/us\" target=\"_blank\">🎧 YouGlish: Hear in context</a> &nbsp;|&nbsp; <a href=\"https://forvo.com/word/blind/#en\" target=\"_blank\">🔊 Forvo: Isolated word</a><br><br><b>Fill the gap:</b><br>The {{c1::blind man}} had a guide dog.",
      "explanation": "<b>Full transcript:</b> blind man<br><br><b>Connected form:</b> <i>blin man</i><br><br><b>Phonetic rules applied:</b><ul><li><code>Cluster Elision</code></li></ul>",
      "spanish": "hombre ciego",
      "usage": "Native: <code>blin man</code><br>Formal: <code>blind man</code><br><a href=\"https://youglish.com/pronounce/blind%20man/english/us\" target=\"_blank\">🎧 YouGlish: Hear in context</a> &nbsp;|&nbsp; <a href=\"https://forvo.com/word/blind/#en\" target=\"_blank\">🔊 Forvo: Isolated word</a>",
      "id": "28f50dc1ec59db4f",
      "full_transcript": "blind man",
      "connected_form": "blin man",
      "gap_text": "The {{c1::blind man}} had a guide dog.",
      "rules_applied": [
        "Cluster Elision"
      ],
      "language": "en",
      "audio_links": {
        "youglish_phrase": "https://youglish.com/pronounce/blind%20man/english/us",
        "forvo_word": "https://forvo.com/word/blind/#en"
      }
    },
    "mnemonics": {
      "palace_name": "",
      "locus_stop": "",
      "mnemonic_scene": "",
      "peg_word": "",
      "phonetic_code": ""
    },
    "interactivity": {
      "analogy": "",
      "interactive_mermaid": "",
      "match_game_data": null
    }
  },
  {
    "id": "9eb658ca48e34137",
    "deck": "03_Languages::English::Phonetics_and_Connected_Speech::01_Cluster_Elision",
    "template": "T9_ListeningChunk",
    "metadata": {
      "difficulty": "intermediate",
      "pillar": "03_Languages",
      "tags": [
        "english",
        "phonetics",
        "connected_speech",
        "cluster_elision",
        "tier_2",
        "cluster_elision"
      ]
    },
    "content": {
      "scenario": "Listening Chunk 🎧: Connected Speech (EN)",
      "text": "<a href=\"https://youglish.com/pronounce/wind%20storm/english/us\" target=\"_blank\">🎧 YouGlish: Hear in context</a> &nbsp;|&nbsp; <a href=\"https://forvo.com/word/wind/#en\" target=\"_blank\">🔊 Forvo: Isolated word</a><br><br><b>Fill the gap:</b><br>There was a heavy {{c1::wind storm}} last night.",
      "explanation": "<b>Full transcript:</b> wind storm<br><br><b>Connected form:</b> <i>win storm</i><br><br><b>Phonetic rules applied:</b><ul><li><code>Cluster Elision</code></li></ul>",
      "spanish": "tormenta de viento",
      "usage": "Native: <code>win storm</code><br>Formal: <code>wind storm</code><br><a href=\"https://youglish.com/pronounce/wind%20storm/english/us\" target=\"_blank\">🎧 YouGlish: Hear in context</a> &nbsp;|&nbsp; <a href=\"https://forvo.com/word/wind/#en\" target=\"_blank\">🔊 Forvo: Isolated word</a>",
      "id": "9eb658ca48e34137",
      "full_transcript": "wind storm",
      "connected_form": "win storm",
      "gap_text": "There was a heavy {{c1::wind storm}} last night.",
      "rules_applied": [
        "Cluster Elision"
      ],
      "language": "en",
      "audio_links": {
        "youglish_phrase": "https://youglish.com/pronounce/wind%20storm/english/us",
        "forvo_word": "https://forvo.com/word/wind/#en"
      }
    },
    "mnemonics": {
      "palace_name": "",
      "locus_stop": "",
      "mnemonic_scene": "",
      "peg_word": "",
      "phonetic_code": ""
    },
    "interactivity": {
      "analogy": "",
      "interactive_mermaid": "",
      "match_game_data": null
    }
  },
  {
    "id": "5e01b8e5a1de57a3",
    "deck": "03_Languages::English::Phonetics_and_Connected_Speech::01_Cluster_Elision",
    "template": "T9_ListeningChunk",
    "metadata": {
      "difficulty": "intermediate",
      "pillar": "03_Languages",
      "tags": [
        "english",
        "phonetics",
        "connected_speech",
        "cluster_elision",
        "tier_2",
        "cluster_elision"
      ]
    },
    "content": {
      "scenario": "Listening Chunk 🎧: Connected Speech (EN)",
      "text": "<a href=\"https://youglish.com/pronounce/kind%20word/english/us\" target=\"_blank\">🎧 YouGlish: Hear in context</a> &nbsp;|&nbsp; <a href=\"https://forvo.com/word/kind/#en\" target=\"_blank\">🔊 Forvo: Isolated word</a><br><br><b>Fill the gap:</b><br>A {{c1::kind word}} makes a big difference.",
      "explanation": "<b>Full transcript:</b> kind word<br><br><b>Connected form:</b> <i>kin word</i><br><br><b>Phonetic rules applied:</b><ul><li><code>Cluster Elision</code></li></ul>",
      "spanish": "palabra amable",
      "usage": "Native: <code>kin word</code><br>Formal: <code>kind word</code><br><a href=\"https://youglish.com/pronounce/kind%20word/english/us\" target=\"_blank\">🎧 YouGlish: Hear in context</a> &nbsp;|&nbsp; <a href=\"https://forvo.com/word/kind/#en\" target=\"_blank\">🔊 Forvo: Isolated word</a>",
      "id": "5e01b8e5a1de57a3",
      "full_transcript": "kind word",
      "connected_form": "kin word",
      "gap_text": "A {{c1::kind word}} makes a big difference.",
      "rules_applied": [
        "Cluster Elision"
      ],
      "language": "en",
      "audio_links": {
        "youglish_phrase": "https://youglish.com/pronounce/kind%20word/english/us",
        "forvo_word": "https://forvo.com/word/kind/#en"
      }
    },
    "mnemonics": {
      "palace_name": "",
      "locus_stop": "",
      "mnemonic_scene": "",
      "peg_word": "",
      "phonetic_code": ""
    },
    "interactivity": {
      "analogy": "",
      "interactive_mermaid": "",
      "match_game_data": null
    }
  },
  {
    "id": "b9db326a56607b0f",
    "deck": "03_Languages::English::Phonetics_and_Connected_Speech::01_Cluster_Elision",
    "template": "T9_ListeningChunk",
    "metadata": {
      "difficulty": "intermediate",
      "pillar": "03_Languages",
      "tags": [
        "english",
        "phonetics",
        "connected_speech",
        "cluster_elision",
        "tier_2",
        "cluster_elision"
      ]
    },
    "content": {
      "scenario": "Listening Chunk 🎧: Connected Speech (EN)",
      "text": "<a href=\"https://youglish.com/pronounce/grand%20standing/english/us\" target=\"_blank\">🎧 YouGlish: Hear in context</a> &nbsp;|&nbsp; <a href=\"https://forvo.com/word/grand/#en\" target=\"_blank\">🔊 Forvo: Isolated word</a><br><br><b>Fill the gap:</b><br>Stop {{c1::grand standing}} in front of everyone.",
      "explanation": "<b>Full transcript:</b> grand standing<br><br><b>Connected form:</b> <i>gran standing</i><br><br><b>Phonetic rules applied:</b><ul><li><code>Cluster Elision</code></li></ul>",
      "spanish": "presumir",
      "usage": "Native: <code>gran standing</code><br>Formal: <code>grand standing</code><br><a href=\"https://youglish.com/pronounce/grand%20standing/english/us\" target=\"_blank\">🎧 YouGlish: Hear in context</a> &nbsp;|&nbsp; <a href=\"https://forvo.com/word/grand/#en\" target=\"_blank\">🔊 Forvo: Isolated word</a>",
      "id": "b9db326a56607b0f",
      "full_transcript": "grand standing",
      "connected_form": "gran standing",
      "gap_text": "Stop {{c1::grand standing}} in front of everyone.",
      "rules_applied": [
        "Cluster Elision"
      ],
      "language": "en",
      "audio_links": {
        "youglish_phrase": "https://youglish.com/pronounce/grand%20standing/english/us",
        "forvo_word": "https://forvo.com/word/grand/#en"
      }
    },
    "mnemonics": {
      "palace_name": "",
      "locus_stop": "",
      "mnemonic_scene": "",
      "peg_word": "",
      "phonetic_code": ""
    },
    "interactivity": {
      "analogy": "",
      "interactive_mermaid": "",
      "match_game_data": null
    }
  },
  {
    "id": "8d44189d46ce331b",
    "deck": "03_Languages::English::Phonetics_and_Connected_Speech::01_Cluster_Elision",
    "template": "T9_ListeningChunk",
    "metadata": {
      "difficulty": "intermediate",
      "pillar": "03_Languages",
      "tags": [
        "english",
        "phonetics",
        "connected_speech",
        "cluster_elision",
        "tier_3",
        "cluster_elision"
      ]
    },
    "content": {
      "scenario": "Listening Chunk 🎧: Connected Speech (EN)",
      "text": "<a href=\"https://youglish.com/pronounce/wild%20card/english/us\" target=\"_blank\">🎧 YouGlish: Hear in context</a> &nbsp;|&nbsp; <a href=\"https://forvo.com/word/wild/#en\" target=\"_blank\">🔊 Forvo: Isolated word</a><br><br><b>Fill the gap:</b><br>They entered as a {{c1::wild card}} team.",
      "explanation": "<b>Full transcript:</b> wild card<br><br><b>Connected form:</b> <i>wil card</i><br><br><b>Phonetic rules applied:</b><ul><li><code>Cluster Elision</code></li></ul>",
      "spanish": "comodín",
      "usage": "Native: <code>wil card</code><br>Formal: <code>wild card</code><br><a href=\"https://youglish.com/pronounce/wild%20card/english/us\" target=\"_blank\">🎧 YouGlish: Hear in context</a> &nbsp;|&nbsp; <a href=\"https://forvo.com/word/wild/#en\" target=\"_blank\">🔊 Forvo: Isolated word</a>",
      "id": "8d44189d46ce331b",
      "full_transcript": "wild card",
      "connected_form": "wil card",
      "gap_text": "They entered as a {{c1::wild card}} team.",
      "rules_applied": [
        "Cluster Elision"
      ],
      "language": "en",
      "audio_links": {
        "youglish_phrase": "https://youglish.com/pronounce/wild%20card/english/us",
        "forvo_word": "https://forvo.com/word/wild/#en"
      }
    },
    "mnemonics": {
      "palace_name": "",
      "locus_stop": "",
      "mnemonic_scene": "",
      "peg_word": "",
      "phonetic_code": ""
    },
    "interactivity": {
      "analogy": "",
      "interactive_mermaid": "",
      "match_game_data": null
    }
  },
  {
    "id": "73bcdeb148b3e9cb",
    "deck": "03_Languages::English::Phonetics_and_Connected_Speech::01_Cluster_Elision",
    "template": "T9_ListeningChunk",
    "metadata": {
      "difficulty": "intermediate",
      "pillar": "03_Languages",
      "tags": [
        "english",
        "phonetics",
        "connected_speech",
        "cluster_elision",
        "tier_3",
        "cluster_elision"
      ]
    },
    "content": {
      "scenario": "Listening Chunk 🎧: Connected Speech (EN)",
      "text": "<a href=\"https://youglish.com/pronounce/bold%20move/english/us\" target=\"_blank\">🎧 YouGlish: Hear in context</a> &nbsp;|&nbsp; <a href=\"https://forvo.com/word/bold/#en\" target=\"_blank\">🔊 Forvo: Isolated word</a><br><br><b>Fill the gap:</b><br>That was a {{c1::bold move}} by the CEO.",
      "explanation": "<b>Full transcript:</b> bold move<br><br><b>Connected form:</b> <i>bol move</i><br><br><b>Phonetic rules applied:</b><ul><li><code>Cluster Elision</code></li></ul>",
      "spanish": "movimiento audaz",
      "usage": "Native: <code>bol move</code><br>Formal: <code>bold move</code><br><a href=\"https://youglish.com/pronounce/bold%20move/english/us\" target=\"_blank\">🎧 YouGlish: Hear in context</a> &nbsp;|&nbsp; <a href=\"https://forvo.com/word/bold/#en\" target=\"_blank\">🔊 Forvo: Isolated word</a>",
      "id": "73bcdeb148b3e9cb",
      "full_transcript": "bold move",
      "connected_form": "bol move",
      "gap_text": "That was a {{c1::bold move}} by the CEO.",
      "rules_applied": [
        "Cluster Elision"
      ],
      "language": "en",
      "audio_links": {
        "youglish_phrase": "https://youglish.com/pronounce/bold%20move/english/us",
        "forvo_word": "https://forvo.com/word/bold/#en"
      }
    },
    "mnemonics": {
      "palace_name": "",
      "locus_stop": "",
      "mnemonic_scene": "",
      "peg_word": "",
      "phonetic_code": ""
    },
    "interactivity": {
      "analogy": "",
      "interactive_mermaid": "",
      "match_game_data": null
    }
  },
  {
    "id": "4de03cd7e2fb8d82",
    "deck": "03_Languages::English::Phonetics_and_Connected_Speech::01_Cluster_Elision",
    "template": "T9_ListeningChunk",
    "metadata": {
      "difficulty": "intermediate",
      "pillar": "03_Languages",
      "tags": [
        "english",
        "phonetics",
        "connected_speech",
        "cluster_elision",
        "tier_3",
        "cluster_elision"
      ]
    },
    "content": {
      "scenario": "Listening Chunk 🎧: Connected Speech (EN)",
      "text": "<a href=\"https://youglish.com/pronounce/gold%20mine/english/us\" target=\"_blank\">🎧 YouGlish: Hear in context</a> &nbsp;|&nbsp; <a href=\"https://forvo.com/word/gold/#en\" target=\"_blank\">🔊 Forvo: Isolated word</a><br><br><b>Fill the gap:</b><br>This business is a real {{c1::gold mine}}.",
      "explanation": "<b>Full transcript:</b> gold mine<br><br><b>Connected form:</b> <i>gol mine</i><br><br><b>Phonetic rules applied:</b><ul><li><code>Cluster Elision</code></li></ul>",
      "spanish": "mina de oro",
      "usage": "Native: <code>gol mine</code><br>Formal: <code>gold mine</code><br><a href=\"https://youglish.com/pronounce/gold%20mine/english/us\" target=\"_blank\">🎧 YouGlish: Hear in context</a> &nbsp;|&nbsp; <a href=\"https://forvo.com/word/gold/#en\" target=\"_blank\">🔊 Forvo: Isolated word</a>",
      "id": "4de03cd7e2fb8d82",
      "full_transcript": "gold mine",
      "connected_form": "gol mine",
      "gap_text": "This business is a real {{c1::gold mine}}.",
      "rules_applied": [
        "Cluster Elision"
      ],
      "language": "en",
      "audio_links": {
        "youglish_phrase": "https://youglish.com/pronounce/gold%20mine/english/us",
        "forvo_word": "https://forvo.com/word/gold/#en"
      }
    },
    "mnemonics": {
      "palace_name": "",
      "locus_stop": "",
      "mnemonic_scene": "",
      "peg_word": "",
      "phonetic_code": ""
    },
    "interactivity": {
      "analogy": "",
      "interactive_mermaid": "",
      "match_game_data": null
    }
  },
  {
    "id": "3159e343b36e641c",
    "deck": "03_Languages::English::Phonetics_and_Connected_Speech::01_Cluster_Elision",
    "template": "T9_ListeningChunk",
    "metadata": {
      "difficulty": "intermediate",
      "pillar": "03_Languages",
      "tags": [
        "english",
        "phonetics",
        "connected_speech",
        "cluster_elision",
        "tier_3",
        "cluster_elision"
      ]
    },
    "content": {
      "scenario": "Listening Chunk 🎧: Connected Speech (EN)",
      "text": "<a href=\"https://youglish.com/pronounce/cold%20cuts/english/us\" target=\"_blank\">🎧 YouGlish: Hear in context</a> &nbsp;|&nbsp; <a href=\"https://forvo.com/word/cold/#en\" target=\"_blank\">🔊 Forvo: Isolated word</a><br><br><b>Fill the gap:</b><br>We had {{c1::cold cuts}} for lunch.",
      "explanation": "<b>Full transcript:</b> cold cuts<br><br><b>Connected form:</b> <i>col cuts</i><br><br><b>Phonetic rules applied:</b><ul><li><code>Cluster Elision</code></li></ul>",
      "spanish": "embutidos",
      "usage": "Native: <code>col cuts</code><br>Formal: <code>cold cuts</code><br><a href=\"https://youglish.com/pronounce/cold%20cuts/english/us\" target=\"_blank\">🎧 YouGlish: Hear in context</a> &nbsp;|&nbsp; <a href=\"https://forvo.com/word/cold/#en\" target=\"_blank\">🔊 Forvo: Isolated word</a>",
      "id": "3159e343b36e641c",
      "full_transcript": "cold cuts",
      "connected_form": "col cuts",
      "gap_text": "We had {{c1::cold cuts}} for lunch.",
      "rules_applied": [
        "Cluster Elision"
      ],
      "language": "en",
      "audio_links": {
        "youglish_phrase": "https://youglish.com/pronounce/cold%20cuts/english/us",
        "forvo_word": "https://forvo.com/word/cold/#en"
      }
    },
    "mnemonics": {
      "palace_name": "",
      "locus_stop": "",
      "mnemonic_scene": "",
      "peg_word": "",
      "phonetic_code": ""
    },
    "interactivity": {
      "analogy": "",
      "interactive_mermaid": "",
      "match_game_data": null
    }
  },
  {
    "id": "2cf320779a9e9517",
    "deck": "03_Languages::English::Phonetics_and_Connected_Speech::01_Cluster_Elision",
    "template": "T9_ListeningChunk",
    "metadata": {
      "difficulty": "intermediate",
      "pillar": "03_Languages",
      "tags": [
        "english",
        "phonetics",
        "connected_speech",
        "cluster_elision",
        "tier_3",
        "cluster_elision"
      ]
    },
    "content": {
      "scenario": "Listening Chunk 🎧: Connected Speech (EN)",
      "text": "<a href=\"https://youglish.com/pronounce/fast%20food/english/us\" target=\"_blank\">🎧 YouGlish: Hear in context</a> &nbsp;|&nbsp; <a href=\"https://forvo.com/word/fast/#en\" target=\"_blank\">🔊 Forvo: Isolated word</a><br><br><b>Fill the gap:</b><br>I try not to eat too much {{c1::fast food}}.",
      "explanation": "<b>Full transcript:</b> fast food<br><br><b>Connected form:</b> <i>fas food</i><br><br><b>Phonetic rules applied:</b><ul><li><code>Cluster Elision</code></li></ul>",
      "spanish": "comida rápida",
      "usage": "Native: <code>fas food</code><br>Formal: <code>fast food</code><br><a href=\"https://youglish.com/pronounce/fast%20food/english/us\" target=\"_blank\">🎧 YouGlish: Hear in context</a> &nbsp;|&nbsp; <a href=\"https://forvo.com/word/fast/#en\" target=\"_blank\">🔊 Forvo: Isolated word</a>",
      "id": "2cf320779a9e9517",
      "full_transcript": "fast food",
      "connected_form": "fas food",
      "gap_text": "I try not to eat too much {{c1::fast food}}.",
      "rules_applied": [
        "Cluster Elision"
      ],
      "language": "en",
      "audio_links": {
        "youglish_phrase": "https://youglish.com/pronounce/fast%20food/english/us",
        "forvo_word": "https://forvo.com/word/fast/#en"
      }
    },
    "mnemonics": {
      "palace_name": "",
      "locus_stop": "",
      "mnemonic_scene": "",
      "peg_word": "",
      "phonetic_code": ""
    },
    "interactivity": {
      "analogy": "",
      "interactive_mermaid": "",
      "match_game_data": null
    }
  },
  {
    "id": "a8918f8827a087bb",
    "deck": "03_Languages::English::Phonetics_and_Connected_Speech::01_Cluster_Elision",
    "template": "T9_ListeningChunk",
    "metadata": {
      "difficulty": "intermediate",
      "pillar": "03_Languages",
      "tags": [
        "english",
        "phonetics",
        "connected_speech",
        "cluster_elision",
        "tier_3",
        "cluster_elision"
      ]
    },
    "content": {
      "scenario": "Listening Chunk 🎧: Connected Speech (EN)",
      "text": "<a href=\"https://youglish.com/pronounce/most%20people/english/us\" target=\"_blank\">🎧 YouGlish: Hear in context</a> &nbsp;|&nbsp; <a href=\"https://forvo.com/word/most/#en\" target=\"_blank\">🔊 Forvo: Isolated word</a><br><br><b>Fill the gap:</b><br>{{c1::Most people}} agree with this decision.",
      "explanation": "<b>Full transcript:</b> most people<br><br><b>Connected form:</b> <i>mos people</i><br><br><b>Phonetic rules applied:</b><ul><li><code>Cluster Elision</code></li></ul>",
      "spanish": "la mayoría de la gente",
      "usage": "Native: <code>mos people</code><br>Formal: <code>most people</code><br><a href=\"https://youglish.com/pronounce/most%20people/english/us\" target=\"_blank\">🎧 YouGlish: Hear in context</a> &nbsp;|&nbsp; <a href=\"https://forvo.com/word/most/#en\" target=\"_blank\">🔊 Forvo: Isolated word</a>",
      "id": "a8918f8827a087bb",
      "full_transcript": "most people",
      "connected_form": "mos people",
      "gap_text": "{{c1::Most people}} agree with this decision.",
      "rules_applied": [
        "Cluster Elision"
      ],
      "language": "en",
      "audio_links": {
        "youglish_phrase": "https://youglish.com/pronounce/most%20people/english/us",
        "forvo_word": "https://forvo.com/word/most/#en"
      }
    },
    "mnemonics": {
      "palace_name": "",
      "locus_stop": "",
      "mnemonic_scene": "",
      "peg_word": "",
      "phonetic_code": ""
    },
    "interactivity": {
      "analogy": "",
      "interactive_mermaid": "",
      "match_game_data": null
    }
  },
  {
    "id": "dc24b4f62fff28af",
    "deck": "03_Languages::English::Phonetics_and_Connected_Speech::01_Cluster_Elision",
    "template": "T9_ListeningChunk",
    "metadata": {
      "difficulty": "intermediate",
      "pillar": "03_Languages",
      "tags": [
        "english",
        "phonetics",
        "connected_speech",
        "cluster_elision",
        "tier_3",
        "cluster_elision"
      ]
    },
    "content": {
      "scenario": "Listening Chunk 🎧: Connected Speech (EN)",
      "text": "<a href=\"https://youglish.com/pronounce/post%20office/english/us\" target=\"_blank\">🎧 YouGlish: Hear in context</a> &nbsp;|&nbsp; <a href=\"https://forvo.com/word/post/#en\" target=\"_blank\">🔊 Forvo: Isolated word</a><br><br><b>Fill the gap:</b><br>Where is the nearest {{c1::post office}}?",
      "explanation": "<b>Full transcript:</b> post office<br><br><b>Connected form:</b> <i>pos office</i><br><br><b>Phonetic rules applied:</b><ul><li><code>Cluster Elision</code></li></ul>",
      "spanish": "oficina de correos",
      "usage": "Native: <code>pos office</code><br>Formal: <code>post office</code><br><a href=\"https://youglish.com/pronounce/post%20office/english/us\" target=\"_blank\">🎧 YouGlish: Hear in context</a> &nbsp;|&nbsp; <a href=\"https://forvo.com/word/post/#en\" target=\"_blank\">🔊 Forvo: Isolated word</a>",
      "id": "dc24b4f62fff28af",
      "full_transcript": "post office",
      "connected_form": "pos office",
      "gap_text": "Where is the nearest {{c1::post office}}?",
      "rules_applied": [
        "Cluster Elision"
      ],
      "language": "en",
      "audio_links": {
        "youglish_phrase": "https://youglish.com/pronounce/post%20office/english/us",
        "forvo_word": "https://forvo.com/word/post/#en"
      }
    },
    "mnemonics": {
      "palace_name": "",
      "locus_stop": "",
      "mnemonic_scene": "",
      "peg_word": "",
      "phonetic_code": ""
    },
    "interactivity": {
      "analogy": "",
      "interactive_mermaid": "",
      "match_game_data": null
    }
  },
  {
    "id": "86c86007b4de01f0",
    "deck": "03_Languages::English::Phonetics_and_Connected_Speech::01_Cluster_Elision",
    "template": "T9_ListeningChunk",
    "metadata": {
      "difficulty": "intermediate",
      "pillar": "03_Languages",
      "tags": [
        "english",
        "phonetics",
        "connected_speech",
        "cluster_elision",
        "tier_3",
        "cluster_elision"
      ]
    },
    "content": {
      "scenario": "Listening Chunk 🎧: Connected Speech (EN)",
      "text": "<a href=\"https://youglish.com/pronounce/west%20coast/english/us\" target=\"_blank\">🎧 YouGlish: Hear in context</a> &nbsp;|&nbsp; <a href=\"https://forvo.com/word/west/#en\" target=\"_blank\">🔊 Forvo: Isolated word</a><br><br><b>Fill the gap:</b><br>They moved to the {{c1::west coast}} last year.",
      "explanation": "<b>Full transcript:</b> west coast<br><br><b>Connected form:</b> <i>wes coast</i><br><br><b>Phonetic rules applied:</b><ul><li><code>Cluster Elision</code></li></ul>",
      "spanish": "costa oeste",
      "usage": "Native: <code>wes coast</code><br>Formal: <code>west coast</code><br><a href=\"https://youglish.com/pronounce/west%20coast/english/us\" target=\"_blank\">🎧 YouGlish: Hear in context</a> &nbsp;|&nbsp; <a href=\"https://forvo.com/word/west/#en\" target=\"_blank\">🔊 Forvo: Isolated word</a>",
      "id": "86c86007b4de01f0",
      "full_transcript": "west coast",
      "connected_form": "wes coast",
      "gap_text": "They moved to the {{c1::west coast}} last year.",
      "rules_applied": [
        "Cluster Elision"
      ],
      "language": "en",
      "audio_links": {
        "youglish_phrase": "https://youglish.com/pronounce/west%20coast/english/us",
        "forvo_word": "https://forvo.com/word/west/#en"
      }
    },
    "mnemonics": {
      "palace_name": "",
      "locus_stop": "",
      "mnemonic_scene": "",
      "peg_word": "",
      "phonetic_code": ""
    },
    "interactivity": {
      "analogy": "",
      "interactive_mermaid": "",
      "match_game_data": null
    }
  },
  {
    "id": "46f426fb5cdf938f",
    "deck": "03_Languages::English::Phonetics_and_Connected_Speech::01_Cluster_Elision",
    "template": "T9_ListeningChunk",
    "metadata": {
      "difficulty": "intermediate",
      "pillar": "03_Languages",
      "tags": [
        "english",
        "phonetics",
        "connected_speech",
        "cluster_elision",
        "tier_3",
        "cluster_elision"
      ]
    },
    "content": {
      "scenario": "Listening Chunk 🎧: Connected Speech (EN)",
      "text": "<a href=\"https://youglish.com/pronounce/east%20coast/english/us\" target=\"_blank\">🎧 YouGlish: Hear in context</a> &nbsp;|&nbsp; <a href=\"https://forvo.com/word/east/#en\" target=\"_blank\">🔊 Forvo: Isolated word</a><br><br><b>Fill the gap:</b><br>I prefer the weather on the {{c1::east coast}}.",
      "explanation": "<b>Full transcript:</b> east coast<br><br><b>Connected form:</b> <i>eas coast</i><br><br><b>Phonetic rules applied:</b><ul><li><code>Cluster Elision</code></li></ul>",
      "spanish": "costa este",
      "usage": "Native: <code>eas coast</code><br>Formal: <code>east coast</code><br><a href=\"https://youglish.com/pronounce/east%20coast/english/us\" target=\"_blank\">🎧 YouGlish: Hear in context</a> &nbsp;|&nbsp; <a href=\"https://forvo.com/word/east/#en\" target=\"_blank\">🔊 Forvo: Isolated word</a>",
      "id": "46f426fb5cdf938f",
      "full_transcript": "east coast",
      "connected_form": "eas coast",
      "gap_text": "I prefer the weather on the {{c1::east coast}}.",
      "rules_applied": [
        "Cluster Elision"
      ],
      "language": "en",
      "audio_links": {
        "youglish_phrase": "https://youglish.com/pronounce/east%20coast/english/us",
        "forvo_word": "https://forvo.com/word/east/#en"
      }
    },
    "mnemonics": {
      "palace_name": "",
      "locus_stop": "",
      "mnemonic_scene": "",
      "peg_word": "",
      "phonetic_code": ""
    },
    "interactivity": {
      "analogy": "",
      "interactive_mermaid": "",
      "match_game_data": null
    }
  },
  {
    "id": "c66e41c52173509a",
    "deck": "03_Languages::English::Phonetics_and_Connected_Speech::01_Cluster_Elision",
    "template": "T9_ListeningChunk",
    "metadata": {
      "difficulty": "intermediate",
      "pillar": "03_Languages",
      "tags": [
        "english",
        "phonetics",
        "connected_speech",
        "cluster_elision",
        "tier_3",
        "cluster_elision"
      ]
    },
    "content": {
      "scenario": "Listening Chunk 🎧: Connected Speech (EN)",
      "text": "<a href=\"https://youglish.com/pronounce/worst%20case/english/us\" target=\"_blank\">🎧 YouGlish: Hear in context</a> &nbsp;|&nbsp; <a href=\"https://forvo.com/word/worst/#en\" target=\"_blank\">🔊 Forvo: Isolated word</a><br><br><b>Fill the gap:</b><br>In the {{c1::worst case}} scenario, we rollback.",
      "explanation": "<b>Full transcript:</b> worst case<br><br><b>Connected form:</b> <i>wors case</i><br><br><b>Phonetic rules applied:</b><ul><li><code>Cluster Elision</code></li></ul>",
      "spanish": "peor de los casos",
      "usage": "Native: <code>wors case</code><br>Formal: <code>worst case</code><br><a href=\"https://youglish.com/pronounce/worst%20case/english/us\" target=\"_blank\">🎧 YouGlish: Hear in context</a> &nbsp;|&nbsp; <a href=\"https://forvo.com/word/worst/#en\" target=\"_blank\">🔊 Forvo: Isolated word</a>",
      "id": "c66e41c52173509a",
      "full_transcript": "worst case",
      "connected_form": "wors case",
      "gap_text": "In the {{c1::worst case}} scenario, we rollback.",
      "rules_applied": [
        "Cluster Elision"
      ],
      "language": "en",
      "audio_links": {
        "youglish_phrase": "https://youglish.com/pronounce/worst%20case/english/us",
        "forvo_word": "https://forvo.com/word/worst/#en"
      }
    },
    "mnemonics": {
      "palace_name": "",
      "locus_stop": "",
      "mnemonic_scene": "",
      "peg_word": "",
      "phonetic_code": ""
    },
    "interactivity": {
      "analogy": "",
      "interactive_mermaid": "",
      "match_game_data": null
    }
  }
]